loristrck/__init__.py
loristrck/__init__.pyi
loristrck/_core.cp39-win_amd64.pyd
loristrck/_core.pyi
loristrck/common.py
loristrck/play.py
loristrck/plot.py
loristrck/py.typed
loristrck/util.py
loristrck/data/README.txt
loristrck/data/libfftw3-3.dll
loristrck-1.7.2.data/scripts/loristrck_analyze
loristrck-1.7.2.data/scripts/loristrck_chord
loristrck-1.7.2.data/scripts/loristrck_pack
loristrck-1.7.2.data/scripts/loristrck_synth
loristrck-1.7.2.dist-info/LICENSE
loristrck-1.7.2.dist-info/METADATA
loristrck-1.7.2.dist-info/WHEEL
loristrck-1.7.2.dist-info/top_level.txt
loristrck-1.7.2.dist-info/RECORD
