Metadata-Version: 2.1
Name: loristrck
Version: 1.7.2
Summary: A wrapper around the partial-tracking library Loris
Home-page: https://github.com/gesellkammer/loristrck
Author: Eduardo Moguillansky
Author-email: eduardo.moguillansky@gmail.com
License: GPL
Download-URL: https://github.com/gesellkammer/loristrck
Platform: Linux
Platform: Mac OS-X
Platform: Windows
Requires-Python: >=3.9
License-File: LICENSE
Requires-Dist: numpy>=1.8
Requires-Dist: numpyx
Requires-Dist: soundfile
Requires-Dist: pysdif3>=1.0.0
